iotboard/__init__.py
iotboard/mqtt_client.py
sdk/__init__.py
sdk/mqtt_client.py
iotboard-1.0.0.dist-info/METADATA
iotboard-1.0.0.dist-info/WHEEL
iotboard-1.0.0.dist-info/top_level.txt
iotboard-1.0.0.dist-info/RECORD
