Metadata-Version: 2.1
Name: iotboard
Version: 1.0.0
Summary: Your SDK description
Home-page: UNKNOWN
Author: Your Name
Author-email: your@email.com
License: UNKNOWN
Platform: UNKNOWN
Requires-Dist: paho-mqtt
